ultraspy/__init__.py
ultraspy/config.py
ultraspy/metrics.py
ultraspy/scan.py
ultraspy/beamformers/__init__.py
ultraspy/beamformers/beamformer.py
ultraspy/beamformers/capon.py
ultraspy/beamformers/das.py
ultraspy/beamformers/fdmas.py
ultraspy/beamformers/options.py
ultraspy/beamformers/pdas.py
ultraspy/beamformers/setups.py
ultraspy/cpu/__init__.py
ultraspy/cpu/display.py
ultraspy/cpu/doppler.py
ultraspy/cpu/post_processing.py
ultraspy/cpu/signal.py
ultraspy/cpu/kernels/numba_cores/__init__.py
ultraspy/cpu/kernels/numba_cores/aperture_ratio.py
ultraspy/cpu/kernels/numba_cores/apodization.py
ultraspy/cpu/kernels/numba_cores/capon.py
ultraspy/cpu/kernels/numba_cores/das.py
ultraspy/cpu/kernels/numba_cores/fdmas.py
ultraspy/cpu/kernels/numba_cores/interpolation.py
ultraspy/cpu/kernels/numba_cores/maths_utils.py
ultraspy/cpu/kernels/numba_cores/pdas.py
ultraspy/cpu/kernels/numba_cores/probe_distances.py
ultraspy/cpu/kernels/numpy_cores/__init__.py
ultraspy/cpu/kernels/numpy_cores/aperture_ratio.py
ultraspy/cpu/kernels/numpy_cores/das.py
ultraspy/cpu/kernels/numpy_cores/fdmas.py
ultraspy/cpu/kernels/numpy_cores/interpolation.py
ultraspy/cpu/kernels/numpy_cores/pdas.py
ultraspy/cpu/kernels/numpy_cores/probe_distances.py
ultraspy/gpu/__init__.py
ultraspy/gpu/display.py
ultraspy/gpu/doppler.py
ultraspy/gpu/gpu_utils.py
ultraspy/gpu/post_processing.py
ultraspy/gpu/signal.py
ultraspy/gpu/kernels/__init__.py
ultraspy/gpu/kernels/beamformers_kernels.py
ultraspy/gpu/kernels/doppler_kernels.py
ultraspy/gpu/kernels/operators_kernels.py
ultraspy/gpu/kernels/signal_kernels.py
ultraspy/gpu/kernels/utils.py
ultraspy/gpu/kernels/beamformers/aperture_ratio.cu
ultraspy/gpu/kernels/beamformers/apodization.cu
ultraspy/gpu/kernels/beamformers/capon.cu
ultraspy/gpu/kernels/beamformers/complex_utils.cu
ultraspy/gpu/kernels/beamformers/das.cu
ultraspy/gpu/kernels/beamformers/fdmas.cu
ultraspy/gpu/kernels/beamformers/interpolation.cu
ultraspy/gpu/kernels/beamformers/pdas.cu
ultraspy-1.2.4.dist-info/AUTHORS.rst
ultraspy-1.2.4.dist-info/LICENSE
ultraspy-1.2.4.dist-info/METADATA
ultraspy-1.2.4.dist-info/WHEEL
ultraspy-1.2.4.dist-info/top_level.txt
ultraspy-1.2.4.dist-info/RECORD
