Metadata-Version: 2.1
Name: ultraspy
Version: 1.2.4
Summary: Ultrasound toolbox for GPU
Home-page: https://gitlab.com/pecarlat/ultraspy
Author: Pierre Ecarlat, Fabien Millioz
Author-email: pierre.ecarlat@gmail.com, fabien.millioz@univ-lyon1.fr
Project-URL: Documentation, https://ultraspy.readthedocs.io/en/latest/
Project-URL: Bug Tracker, https://gitlab.com/pecarlat/ultraspy/-/issues/
Keywords: ultrasound,python,beamforming,doppler
Classifier: Programming Language :: Python :: 3
Classifier: License :: OSI Approved :: MIT License
Classifier: Operating System :: OS Independent
Requires-Python: >=3.8
License-File: LICENSE
License-File: AUTHORS.rst
Requires-Dist: scipy >=1.10.1
Requires-Dist: matplotlib >=3.6.3
Requires-Dist: easydict >=1.10
Requires-Dist: numba >=0.56.4
Requires-Dist: h5py >=3.8.0
Requires-Dist: py7zr >=0.20.5
